pydub/__init__.py
pydub/audio_segment.py
pydub/effects.py
pydub/exceptions.py
pydub/generators.py
pydub/logging_utils.py
pydub/playback.py
pydub/pyaudioop.py
pydub/scipy_effects.py
pydub/silence.py
pydub/utils.py
pydub_ng-0.2.0.dist-info/AUTHORS
pydub_ng-0.2.0.dist-info/LICENSE
pydub_ng-0.2.0.dist-info/METADATA
pydub_ng-0.2.0.dist-info/WHEEL
pydub_ng-0.2.0.dist-info/top_level.txt
pydub_ng-0.2.0.dist-info/RECORD
